arcane/datastore/__init__.py
arcane/datastore/const.py
arcane/datastore/datastore.py
arcane_datastore-1.1.15.dist-info/METADATA
arcane_datastore-1.1.15.dist-info/WHEEL
arcane_datastore-1.1.15.dist-info/RECORD
