Metadata-Version: 2.3
Name: arcane-datastore
Version: 1.1.15
Summary: Override datastore client
Author: Arcane
Author-email: product@wearcane.com
Requires-Python: >=3.7,<4.0
Classifier: Programming Language :: Python :: 3
Classifier: Programming Language :: Python :: 3.7
Classifier: Programming Language :: Python :: 3.8
Classifier: Programming Language :: Python :: 3.9
Classifier: Programming Language :: Python :: 3.10
Classifier: Programming Language :: Python :: 3.11
Classifier: Programming Language :: Python :: 3.12
Classifier: Programming Language :: Python :: 3.13
Requires-Dist: arcane-core (>=1.6.0,<2.0.0)
Requires-Dist: backoff (>=1.10.0)
Requires-Dist: google-cloud-datastore (>=2.11.0,<3.0.0)
